alphasquared/__init__.py
alphasquared/alphasquared.py
alphasquared/test_alphasquared.py
alphasquared_py-0.3.1.dist-info/licenses/LICENSE
alphasquared_py-0.3.1.dist-info/METADATA
alphasquared_py-0.3.1.dist-info/WHEEL
alphasquared_py-0.3.1.dist-info/top_level.txt
alphasquared_py-0.3.1.dist-info/RECORD
